<?xml version="1.0" encoding="utf-8"?>
<CharacterActionSetLayerSort xmlns:xsi="http://www.w3.org/2001/XMLSchema-instance" xmlns:xsd="http://www.w3.org/2001/XMLSchema">
	<Male>
	  <Action Name="DEFAULT">
		<Layers />
		<Dirs>
		  <Dir ID="0" Values="14,16,13,1,4,9,7,5,6,12,8,0" />
		  <Dir ID="1" Values="14,16,13,9,7,4,1,5,12,6,8,0" />
		  <Dir ID="2" Values="9,7,12,13,14,5,16,4,1,0,6,8" />
		  <Dir ID="3" Values="9,7,12,13,5,14,16,4,1,0,8,6" />
		  <Dir ID="4" Values="12,13,8,6,5,14,16,4,1,0,7,9" />
		  <Dir ID="5" Values="8,6,12,13,5,14,16,4,1,0,9,7" />
		  <Dir ID="6" Values="8,6,12,13,14,5,16,4,1,0,9,7" />
		  <Dir ID="7" Values="14,16,13,4,1,8,6,5,12,0,9,7" />
		  <Dir ID="8" Values="12,13,14,8,6,9,5,16,4,0,1,7" />
		  <Dir ID="9" Values="12,13,14,8,6,9,5,16,4,0,1,7" />
		  <Dir ID="10" Values="12,13,14,8,6,9,5,16,4,0,1,7" />
		  <Dir ID="11" Values="12,13,14,8,6,5,16,4,0,1,9,7" />
		  <Dir ID="12" Values="12,13,14,8,6,5,16,4,0,1,9,7" />
		  <Dir ID="13" Values="12,13,14,8,6,5,16,4,1,0,7,9" />
		  <Dir ID="14" Values="12,13,14,6,8,5,16,4,1,0,7,9" />
		  <Dir ID="15" Values="12,13,14,5,16,0,1,6,8,7,9,4" />
		</Dirs>
	  </Action>
	  <Action Name="RangeWStand">
		<Layers />
		<Dirs>
		  <Dir ID="0" Values="14,16,13,1,4,7,5,6,8,9,0,12" />
		  <Dir ID="1" Values="14,16,13,7,4,1,5,12,6,8,0,9" />
		  <Dir ID="4" Values="12,13,9,8,6,5,14,16,4,1,0,7" />
		  <Dir ID="5" Values="8,6,12,13,9,5,14,16,4,1,0,7" />
		  <Dir ID="6" Values="8,6,12,13,14,1,4,5,16,0,9,7" />
		</Dirs>
	  </Action>
	  <Action Name="RangeWWalk">
		<Layers>
		  <Layer ID="30" Values="7,12,13,14,5,16,4,1,0,9,6,8" />
		  <Layer ID="31" Values="7,12,13,14,5,16,4,1,0,9,6,8" />
		  <Layer ID="44" Values="7,12,13,14,5,16,4,1,0,9,6,8" />
		</Layers>
		<Dirs>
		  <Dir ID="0" Values="14,16,13,1,4,7,5,6,8,0,12,9" />
		  <Dir ID="1" Values="14,16,13,7,4,1,5,12,6,8,0,9" />
		  <Dir ID="4" Values="12,13,9,8,6,5,14,16,4,1,0,7" />
		  <Dir ID="5" Values="8,6,12,13,9,5,14,16,4,1,0,7" />
		</Dirs>
	  </Action>
	  <Action Name="RangeWRun">
		<Layers />
		<Dirs>
		  <Dir ID="0" Values="14,16,13,1,4,7,5,6,8,0,9,12" />
		  <Dir ID="1" Values="14,16,13,7,4,1,5,12,6,8,0,9" />
		  <Dir ID="4" Values="12,13,9,8,6,5,14,16,4,1,0,7" />
		  <Dir ID="5" Values="8,6,12,13,5,14,16,9,4,1,0,7" />
		</Dirs>
	  </Action>
	  <Action Name="RangeWWound">
		<Layers />
		<Dirs>
		  <Dir ID="0" Values="14,16,13,1,4,7,5,6,8,0,12,9" />
		  <Dir ID="1" Values="14,16,13,7,4,1,5,12,6,8,0,9" />
		  <Dir ID="4" Values="12,13,9,8,6,5,14,16,4,1,0,7" />
		  <Dir ID="5" Values="8,6,12,13,5,9,14,16,4,1,0,7" />
		</Dirs>
	  </Action>
	  <Action Name="RangeWDie">
		<Layers>
		  <Layer ID="12" Values="14,13,1,4,7,5,6,8,0,12,9,16" />
		  <Layer ID="13" Values="14,13,1,4,7,5,6,8,0,12,9,16" />
		  <Layer ID="14" Values="14,13,1,4,7,5,6,8,0,12,9,16" />
		  <Layer ID="117" Values="14,13,4,1,8,6,5,12,0,9,7,16" />
		  <Layer ID="118" Values="14,13,4,1,8,6,5,12,0,9,7,16" />
		  <Layer ID="119" Values="14,13,4,1,8,6,5,12,0,9,7,16" />
		</Layers>
		<Dirs>
		  <Dir ID="0" Values="14,16,13,1,4,7,5,6,8,0,12,9" />
		  <Dir ID="1" Values="14,13,7,4,1,5,12,6,8,0,9,16" />
		  <Dir ID="4" Values="12,13,9,8,6,5,14,16,4,1,0,7" />
		  <Dir ID="5" Values="8,6,12,13,9,5,14,16,4,1,0,7" />
		</Dirs>
	  </Action>
	  <Action Name="RangeWCut">
		<Layers>
		  <Layer ID="18" Values="14,16,13,9,7,4,1,5,12,6,8,0" />
		  <Layer ID="19" Values="14,16,13,9,7,4,1,5,12,6,8,0" />
		  <Layer ID="20" Values="14,16,13,9,7,4,1,5,12,6,8,0" />
		  <Layer ID="21" Values="14,16,13,9,7,4,1,5,12,6,8,0" />
		  <Layer ID="22" Values="14,16,13,9,7,4,1,5,12,6,8,0" />
		  <Layer ID="26" Values="7,12,13,14,5,16,4,1,0,6,8,9" />
		  <Layer ID="27" Values="7,12,13,14,5,16,4,1,0,6,8,9" />
		  <Layer ID="28" Values="7,12,13,14,5,16,4,1,0,6,8,9" />
		  <Layer ID="29" Values="7,12,13,14,5,16,4,1,0,6,8,9" />
		  <Layer ID="39" Values="7,12,13,5,14,16,4,1,0,8,6,9" />
		  <Layer ID="40" Values="7,12,13,5,14,16,4,1,0,8,6,9" />
		  <Layer ID="52" Values="12,13,8,6,7,5,14,16,4,1,0,9" />
		  <Layer ID="42" Values="9,7,12,13,6,5,14,16,4,1,0,8" />
		  <Layer ID="43" Values="9,7,12,13,6,5,14,16,4,1,0,8" />
		  <Layer ID="44" Values="9,7,12,13,6,5,14,16,4,1,0,8" />
		  <Layer ID="50" Values="12,13,9,8,6,7,5,14,16,4,1,0" />
		  <Layer ID="51" Values="12,13,9,8,6,7,5,14,16,4,1,0" />
		  <Layer ID="53" Values="12,13,9,8,6,7,5,14,16,4,1,0" />
		  <Layer ID="90" Values="14,16,13,4,1,8,5,6,12,0,9,7" />
		  <Layer ID="91" Values="14,16,13,4,1,8,5,6,12,0,9,7" />
		  <Layer ID="92" Values="14,16,13,4,1,8,5,6,12,0,9,7" />
		  <Layer ID="93" Values="14,16,13,4,1,8,5,6,12,0,9,7" />
		  <Layer ID="2" Values="14,16,13,1,4,5,7,6,8,0,12,9" />
		  <Layer ID="3" Values="14,16,13,1,4,5,7,6,8,0,12,9" />
		  <Layer ID="4" Values="14,16,13,1,4,5,7,6,8,0,12,9" />
		</Layers>
		<Dirs>
		  <Dir ID="0" Values="14,16,13,1,4,7,5,6,8,0,12,9" />
		  <Dir ID="1" Values="14,16,13,7,4,1,5,12,6,8,0,9" />
		  <Dir ID="4" Values="12,13,9,8,6,5,14,16,4,1,0,7" />
		  <Dir ID="5" Values="8,6,12,13,5,14,16,4,1,9,7,0" />
		  <Dir ID="6" Values="8,6,12,13,14,5,16,4,1,9,7,0" />
		</Dirs>
	  </Action>
	  <Action Name="RangeWPuncture">
		<Layers>
		  <Layer ID="12" Values="14,16,13,7,4,1,5,12,6,8,0,9" />
		  <Layer ID="38" Values="9,7,12,13,6,5,14,16,4,1,0,8" />
		  <Layer ID="37" Values="9,7,12,13,6,5,14,16,4,1,0,8" />
		  <Layer ID="39" Values="9,12,13,6,5,7,14,16,4,1,0,8" />
		  <Layer ID="40" Values="9,12,13,6,5,7,14,16,4,1,0,8" />
		  <Layer ID="41" Values="9,7,12,13,6,5,14,16,4,1,0,8" />
		  <Layer ID="87" Values="14,16,13,4,1,8,5,6,12,0,9,7" />
		  <Layer ID="88" Values="14,16,13,4,1,8,5,6,12,0,9,7" />
		  <Layer ID="89" Values="14,16,13,4,1,8,5,6,12,0,9,7" />
		</Layers>
		<Dirs>
		  <Dir ID="0" Values="14,16,13,1,4,7,5,6,8,0,12,9" />
		  <Dir ID="4" Values="12,13,9,8,6,5,14,16,4,1,0,7" />
		  <Dir ID="5" Values="8,6,12,13,5,14,16,4,1,9,7,0" />
		</Dirs>
	  </Action>
	  <Action Name="RangeWMagic">
		<Layers>
		  <Layer ID="32" Values="7,12,13,14,5,16,4,1,0,6,8,9" />
		  <Layer ID="33" Values="7,12,13,14,5,16,4,1,0,6,8,9" />
		  <Layer ID="34" Values="7,12,13,14,5,16,4,1,0,6,8,9" />
		  <Layer ID="35" Values="7,12,13,14,5,16,4,1,0,6,8,9" />
		  <Layer ID="31" Values="7,12,13,14,5,16,4,1,0,6,8,9" />
		  <Layer ID="36" Values="7,12,13,14,5,16,4,1,0,6,8,9" />
		  <Layer ID="71" Values="8,6,12,13,5,14,16,4,1,0,7,9" />
		  <Layer ID="72" Values="8,6,12,13,5,14,16,4,1,0,7,9" />
		  <Layer ID="73" Values="8,6,12,13,5,14,16,4,1,0,7,9" />
		  <Layer ID="74" Values="8,6,12,13,5,14,16,4,1,0,7,9" />
		  <Layer ID="75" Values="8,6,12,13,5,14,16,4,1,0,7,9" />
		</Layers>
		<Dirs>
		  <Dir ID="0" Values="14,16,13,1,4,7,5,6,8,0,12,9" />
		  <Dir ID="1" Values="14,16,13,7,4,1,5,12,6,8,0,9" />
		  <Dir ID="4" Values="12,13,9,8,6,5,14,16,4,1,0,7" />
		  <Dir ID="5" Values="9,8,6,12,13,5,14,16,4,1,0,7" />
		  <Dir ID="7" Values="14,16,13,4,1,8,6,5,12,0,7,9" />
		</Dirs>
	  </Action>
	  <Action Name="RideStand">
		<Layers />
		<Dirs>
		  <Dir ID="4" Values="12,13,8,6,5,14,16,0,7,4,9,1" />
		  <Dir ID="0" Values="14,16,13,1,4,9,7,6,5,12,8,0" />
		  <Dir ID="5" Values="8,6,12,13,5,14,16,0,7,4,9,1" />
		</Dirs>
	  </Action>
	  <Action Name="RideStand1">
		<Layers />
		<Dirs>
		  <Dir ID="4" Values="12,13,8,6,5,14,16,0,7,4,9,1" />
		  <Dir ID="0" Values="14,16,13,1,4,9,7,6,5,12,8,0" />
		  <Dir ID="5" Values="8,6,12,13,5,14,16,0,7,4,9,1" />
		</Dirs>
	  </Action>
	  <Action Name="RideStand2">
		<Layers />
		<Dirs>
		  <Dir ID="4" Values="12,13,8,6,5,14,16,0,7,4,9,1" />
		  <Dir ID="0" Values="14,16,13,1,4,9,7,6,5,12,8,0" />
		  <Dir ID="5" Values="8,6,12,13,5,14,16,0,7,4,9,1" />
		</Dirs>
	  </Action>
	  <Action Name="RideRun">
		<Layers />
		<Dirs>
		  <Dir ID="4" Values="12,13,8,6,5,14,16,0,9,7,4,1" />
		  <Dir ID="0" Values="14,16,13,1,9,4,7,5,6,12,8,0" />
		  <Dir ID="5" Values="8,6,12,13,5,14,16,0,9,7,4,1" />
		  <Dir ID="6" Values="8,6,12,13,14,5,16,0,9,7,4,1" />
		  <Dir ID="7" Values="14,16,13,8,6,5,12,4,1,0,9,7" />
		</Dirs>
	  </Action>
	  <Action Name="RideWalk">
		<Layers />
		<Dirs>
		  <Dir ID="0" Values="14,16,13,1,4,9,7,6,5,12,8,0" />
		  <Dir ID="4" Values="12,13,8,6,5,14,16,0,7,4,9,1" />
		  <Dir ID="5" Values="8,6,12,13,5,14,16,0,7,4,9,1" />
		</Dirs>
	  </Action>
	  <Action Name="RideWound">
		<Layers>
		  <Layer ID="2" Values="14,16,13,1,4,9,7,8,6,5,12,0" />
		</Layers>
		<Dirs>
		  <Dir ID="4" Values="12,13,8,6,5,14,16,0,9,7,4,1" />
		  <Dir ID="0" Values="14,16,13,1,4,9,7,6,5,12,8,0" />
		</Dirs>
	  </Action>
	  <Action Name="RideMagic">
		<Layers>
		  <Layer ID="8" Values="14,16,13,1,4,7,5,12,8,0,9,6" />
		  <Layer ID="9" Values="14,16,13,1,4,7,5,12,8,0,9,6" />
		  <Layer ID="10" Values="14,16,13,1,4,7,5,12,8,0,9,6" />
		  <Layer ID="0" Values="14,16,13,1,4,9,7,6,5,12,8,0" />
		  <Layer ID="1" Values="14,16,13,1,4,9,7,6,5,12,8,0" />
		  <Layer ID="2" Values="14,16,13,1,4,9,7,6,5,12,8,0" />
		  <Layer ID="11" Values="14,16,13,1,4,9,7,6,5,12,8,0" />
		</Layers>
		<Dirs>
		  <Dir ID="0" Values="14,16,13,1,4,9,7,5,12,8,0,6" />
		  <Dir ID="4" Values="12,13,8,5,6,14,16,0,7,4,9,1" />
		</Dirs>
	  </Action>
	  <Action Name="RideDie">
		<Layers>
		  <Layer ID="6" Values="14,16,13,1,4,7,5,6,12,8,0,9" />
		  <Layer ID="7" Values="14,16,13,1,4,7,5,6,12,8,0,9" />
		  <Layer ID="8" Values="14,16,13,1,4,7,5,6,12,8,0,9" />
		  <Layer ID="9" Values="14,16,13,1,4,5,6,12,8,0,7,9" />
		  <Layer ID="10" Values="14,16,13,1,4,5,6,12,8,0,7,9" />
		  <Layer ID="11" Values="8,14,16,13,1,4,5,6,12,0,7,9" />
		  <Layer ID="13" Values="8,14,16,13,1,4,5,6,12,0,7,9" />
		  <Layer ID="12" Values="8,14,16,13,1,4,5,6,12,0,7,9" />
		  <Layer ID="23" Values="14,16,13,4,1,5,12,6,8,0,7,9" />
		  <Layer ID="24" Values="14,16,13,4,1,5,12,6,8,0,7,9" />
		  <Layer ID="25" Values="14,16,13,4,1,5,12,6,8,0,7,9" />
		  <Layer ID="26" Values="14,16,13,4,1,5,12,6,8,0,9,7" />
		  <Layer ID="27" Values="14,16,13,4,1,5,12,6,8,0,9,7" />
		  <Layer ID="37" Values="6,12,13,14,5,16,4,1,0,8,7,9" />
		  <Layer ID="38" Values="6,12,13,14,5,16,4,1,0,8,7,9" />
		  <Layer ID="39" Values="6,12,13,14,5,16,4,1,0,8,7,9" />
		  <Layer ID="40" Values="6,12,13,14,5,16,4,1,0,8,7,9" />
		  <Layer ID="41" Values="6,12,13,14,5,16,4,1,0,8,7,9" />
		  <Layer ID="51" Values="6,12,13,5,14,16,4,1,0,8,7,9" />
		  <Layer ID="52" Values="6,12,13,5,14,16,4,1,0,8,7,9" />
		  <Layer ID="53" Values="6,12,13,5,14,16,4,1,0,8,7,9" />
		  <Layer ID="54" Values="6,12,13,5,14,16,4,1,0,8,7,9" />
		  <Layer ID="55" Values="6,12,13,5,14,16,4,1,0,8,7,9" />
		</Layers>
		<Dirs>
		  <Dir ID="4" Values="12,13,8,6,5,14,16,1,0,7,4,9" />
		</Dirs>
	  </Action>
	  <Action Name="RideCut">
		<Layers>
		  <Layer ID="4" Values="14,16,13,1,4,7,5,6,12,8,0,9" />
		  <Layer ID="7" Values="14,16,13,1,4,7,9,5,6,12,8,0" />
		  <Layer ID="8" Values="14,16,13,1,4,5,7,12,8,6,0,9" />
		  <Layer ID="9" Values="14,16,13,1,4,5,7,12,9,8,6,0" />
		  <Layer ID="10" Values="14,16,13,1,4,5,12,8,6,0,9,7" />
		  <Layer ID="56" Values="12,13,5,8,6,14,16,9,7,0,4,1" />
		  <Layer ID="88" Values="14,16,13,4,1,8,6,5,12,0,7,9" />
		  <Layer ID="89" Values="14,16,13,4,1,8,6,5,12,0,7,9" />
		  <Layer ID="90" Values="14,16,13,4,1,8,6,5,12,0,7,9" />
		  <Layer ID="11" Values="14,16,13,1,4,9,7,5,12,8,6,0" />
		  <Layer ID="55" Values="12,13,5,8,6,14,16,0,7,4,1,9" />
		  <Layer ID="57" Values="12,13,5,6,8,14,16,4,1,0,9,7" />
		  <Layer ID="58" Values="12,13,5,6,8,14,16,1,0,9,7,4" />
		  <Layer ID="48" Values="12,13,8,5,6,14,16,0,7,1,4,9" />
		</Layers>
		<Dirs>
		  <Dir ID="4" Values="12,13,8,5,6,14,16,0,7,4,1,9" />
		</Dirs>
	  </Action>
	  <Action Name="RidePuncture">
		<Layers>
		  <Layer ID="5" Values="14,16,13,1,4,5,12,8,6,0,9,7" />
		  <Layer ID="6" Values="14,16,13,1,4,5,6,12,8,0,9,7" />
		  <Layer ID="10" Values="14,16,13,1,4,7,5,12,8,6,0,9" />
		  <Layer ID="11" Values="14,16,13,1,4,5,12,8,6,0,9,7" />
		  <Layer ID="12" Values="14,16,13,1,4,5,12,8,6,0,9,7" />
		  <Layer ID="13" Values="14,16,13,1,4,9,7,5,12,8,6,0" />
		  <Layer ID="61" Values="12,13,9,5,8,6,14,16,1,0,7,4" />
		  <Layer ID="62" Values="12,13,9,5,8,6,14,16,1,0,7,4" />
		  <Layer ID="66" Values="9,12,13,5,8,6,14,16,0,7,4,1" />
		  <Layer ID="67" Values="9,12,13,5,8,6,14,16,0,7,4,1" />
		  <Layer ID="68" Values="9,12,13,5,8,6,14,16,0,7,4,1" />
		</Layers>
		<Dirs>
		  <Dir ID="1" Values="14,16,13,9,7,4,1,5,12,8,6,0" />
		  <Dir ID="4" Values="12,13,8,6,5,14,16,0,7,4,1,9" />
		</Dirs>
	  </Action>
	  <Action Name="DoubleWRun">
		<Layers />
		<Dirs>
		  <Dir ID="0" Values="1,7,6,16,5,9,0,12,8,14,13,4" />
		  <Dir ID="1" Values="14,16,13,9,7,4,1,5,8,12,6,0" />
		  <Dir ID="4" Values="12,13,8,6,9,5,7,14,16,4,1,0" />
		</Dirs>
	  </Action>
	  <Action Name="DoubleWStand">
		<Layers>
		  <Layer ID="8" Values="13,1,4,7,16,5,6,0,12,9,8,14" />
		</Layers>
		<Dirs>
		  <Dir ID="0" Values="14,16,13,1,4,7,5,6,0,12,9,8" />
		  <Dir ID="4" Values="9,12,13,8,6,5,14,16,4,1,0,7" />
		  <Dir ID="7" Values="14,16,13,4,1,8,6,5,12,0,7,9" />
		  <Dir ID="6" Values="8,6,12,13,14,5,16,4,1,0,7,9" />
		</Dirs>
	  </Action>
	  <Action Name="FreeRun">
		<Layers>
		  <Layer ID="5" Values="14,16,13,1,4,9,7,5,6,8,0,12" />
		  <Layer ID="6" Values="14,16,13,1,4,9,7,5,6,8,0,12" />
		  <Layer ID="0" Values="14,16,13,1,4,7,6,5,8,0,12,9" />
		  <Layer ID="10" Values="14,16,13,1,4,7,6,5,8,9,0,12" />
		</Layers>
		<Dirs>
		  <Dir ID="0" Values="14,16,13,1,4,9,7,6,5,8,0,12" />
		  <Dir ID="4" Values="12,13,8,6,7,5,14,16,4,1,0,9" />
		</Dirs>
	  </Action>
	  <Action Name="DoubleWWalk">
		<Layers />
		<Dirs>
		  <Dir ID="0" Values="14,16,13,1,4,7,6,5,0,12,8,9" />
		  <Dir ID="4" Values="9,7,12,13,8,6,14,4,5,16,1,0" />
		  <Dir ID="1" Values="14,16,13,7,4,1,12,9,5,6,8,0" />
		</Dirs>
	  </Action>
	  <Action Name="FreeWalk">
		<Layers>
		  <Layer ID="0" Values="14,16,13,1,4,9,6,7,5,8,0,12" />
		  <Layer ID="1" Values="14,16,13,1,4,9,7,6,5,8,0,12" />
		  <Layer ID="2" Values="14,16,13,1,4,9,7,6,5,8,0,12" />
		  <Layer ID="3" Values="14,16,13,1,4,9,7,6,5,8,0,12" />
		  <Layer ID="4" Values="14,16,13,1,4,9,6,7,5,8,0,12" />
		  <Layer ID="11" Values="14,16,13,1,4,9,7,6,5,8,0,12" />
		  <Layer ID="12" Values="14,16,13,1,4,9,7,6,5,8,0,12" />
		  <Layer ID="13" Values="14,16,13,1,4,9,7,6,5,8,0,12" />
		  <Layer ID="14" Values="14,16,13,1,4,9,7,6,5,8,0,12" />
		  <Layer ID="5" Values="14,16,13,1,4,9,7,6,5,8,0,12" />
		  <Layer ID="10" Values="14,16,13,1,4,9,7,6,5,8,0,12" />
		  <Layer ID="9" Values="14,16,13,1,4,9,7,6,5,8,0,12" />
		  <Layer ID="8" Values="14,16,13,1,4,9,7,6,5,8,0,12" />
		</Layers>
		<Dirs>
		  <Dir ID="0" Values="14,16,13,1,4,9,7,6,5,8,0,12" />
		  <Dir ID="4" Values="12,13,8,6,7,5,14,16,4,1,0,9" />
		</Dirs>
	  </Action>
	  <Action Name="DoubleWWound">
		<Layers />
		<Dirs>
		  <Dir ID="0" Values="14,16,13,1,4,7,5,0,6,8,12,9" />
		  <Dir ID="1" Values="14,16,13,7,4,1,5,12,6,8,0,9" />
		  <Dir ID="3" Values="9,7,12,13,8,5,14,16,4,1,0,6" />
		  <Dir ID="4" Values="12,13,8,6,5,14,16,4,9,1,0,7" />
		  <Dir ID="6" Values="6,12,13,14,5,16,4,1,0,7,8,9" />
		  <Dir ID="7" Values="14,16,13,4,1,6,5,12,0,8,7,9" />
		  <Dir ID="2" Values="9,7,12,13,14,5,16,4,1,8,0,6" />
		</Dirs>
	  </Action>
	  <Action Name="DoubleWDie">
		<Layers>
		  <Layer ID="71" Values="8,9,7,12,13,5,14,16,4,1,0,6" />
		</Layers>
		<Dirs>
		  <Dir ID="0" Values="14,16,13,1,4,7,5,6,8,9,0,12" />
		  <Dir ID="4" Values="12,13,8,6,9,5,14,16,4,1,0,7" />
		</Dirs>
	  </Action>
	  <Action Name="DoubleWPound">
		<Layers>
		  <Layer ID="57" Values="12,13,8,6,14,4,1,9,0,5,16,7" />
		  <Layer ID="7" Values="14,16,13,1,4,5,6,8,0,9,7,12" />
		  <Layer ID="8" Values="14,16,13,1,4,5,6,8,0,9,7,12" />
		  <Layer ID="55" Values="12,13,8,6,14,4,1,0,9,7,5,16" />
		  <Layer ID="56" Values="12,13,8,14,4,1,0,9,6,5,16,7" />
		</Layers>
		<Dirs>
		  <Dir ID="0" Values="14,16,13,1,4,7,5,6,8,0,9,12" />
		  <Dir ID="1" Values="14,16,13,9,7,4,1,5,12,6,0,8" />
		  <Dir ID="4" Values="12,13,8,6,14,4,1,0,9,5,16,7" />
		  <Dir ID="7" Values="14,16,13,4,1,8,6,5,12,0,7,9" />
		</Dirs>
	  </Action>
	  <Action Name="DoubleWPull">
		<Layers>
		  <Layer ID="56" Values="9,7,12,13,5,14,16,4,1,0,8,6" />
		  <Layer ID="57" Values="9,7,12,13,5,14,16,4,1,0,8,6" />
		  <Layer ID="58" Values="9,7,12,13,5,14,16,4,1,0,8,6" />
		  <Layer ID="60" Values="9,7,12,13,8,5,14,16,4,1,0,6" />
		  <Layer ID="61" Values="9,7,12,13,8,5,14,16,4,1,0,6" />
		  <Layer ID="62" Values="9,7,12,13,8,5,14,16,4,1,0,6" />
		  <Layer ID="66" Values="12,13,8,9,6,5,7,14,16,4,1,0" />
		  <Layer ID="28" Values="14,16,13,7,4,1,5,12,0,8,6,9" />
		  <Layer ID="29" Values="14,16,13,7,4,1,5,12,0,8,6,9" />
		  <Layer ID="30" Values="14,16,13,7,4,1,5,12,0,8,6,9" />
		  <Layer ID="31" Values="14,16,13,7,4,1,5,12,0,8,6,9" />
		  <Layer ID="40" Values="9,7,12,13,14,5,16,4,1,0,6,8" />
		  <Layer ID="41" Values="9,7,12,13,14,5,16,4,1,0,6,8" />
		  <Layer ID="42" Values="9,7,12,13,14,5,16,4,1,0,6,8" />
		  <Layer ID="69" Values="12,13,9,8,7,5,6,14,16,4,1,0" />
		  <Layer ID="70" Values="12,13,9,8,7,5,6,14,16,4,1,0" />
		  <Layer ID="71" Values="12,13,9,8,7,5,6,14,16,4,1,0" />
		  <Layer ID="72" Values="12,13,9,8,7,5,6,14,16,4,1,0" />
		  <Layer ID="73" Values="12,13,9,8,7,5,6,14,16,4,1,0" />
		  <Layer ID="124" Values="14,16,13,4,1,5,6,12,0,8,7,9" />
		  <Layer ID="125" Values="14,16,13,4,1,5,6,12,0,8,7,9" />
		  <Layer ID="126" Values="14,16,13,4,1,5,6,12,0,8,7,9" />
		</Layers>
		<Dirs>
		  <Dir ID="0" Values="14,16,13,1,4,5,6,7,0,8,12,9" />
		  <Dir ID="1" Values="14,16,13,7,4,1,5,12,0,6,8,9" />
		  <Dir ID="2" Values="9,7,12,13,14,5,16,4,1,0,8,6" />
		  <Dir ID="4" Values="12,13,9,8,6,5,7,14,16,4,1,0" />
		  <Dir ID="7" Values="14,16,13,4,1,6,5,12,0,8,7,9" />
		  <Dir ID="3" Values="9,7,12,13,5,14,16,4,8,1,0,6" />
		</Dirs>
	  </Action>
	  <Action Name="DoubleWMagic">
		<Layers>
		  <Layer ID="46" Values="9,7,12,13,14,5,16,4,1,0,6,8" />
		  <Layer ID="47" Values="9,7,12,13,14,5,16,4,1,0,6,8" />
		  <Layer ID="4" Values="14,16,13,1,4,8,6,5,7,0,9,12" />
		  <Layer ID="6" Values="14,16,13,1,4,6,5,7,8,9,0,12" />
		  <Layer ID="5" Values="14,16,13,1,4,6,8,5,7,9,0,12" />
		  <Layer ID="8" Values="14,16,13,1,4,8,6,5,9,7,0,12" />
		  <Layer ID="7" Values="14,16,13,1,4,8,6,5,7,9,0,12" />
		  <Layer ID="9" Values="14,16,13,1,4,8,6,5,9,7,0,12" />
		  <Layer ID="2" Values="14,16,13,1,4,6,5,7,8,9,0,12" />
		  <Layer ID="3" Values="14,16,13,1,4,6,5,7,8,9,0,12" />
		  <Layer ID="10" Values="14,16,13,1,4,8,5,6,9,7,0,12" />
		  <Layer ID="11" Values="14,16,13,1,4,8,5,6,9,7,0,12" />
		  <Layer ID="12" Values="14,16,13,1,4,8,5,6,9,7,0,12" />
		  <Layer ID="13" Values="14,16,13,1,4,8,5,6,9,7,0,12" />
		  <Layer ID="14" Values="14,16,13,1,4,8,5,6,9,7,0,12" />
		  <Layer ID="15" Values="14,16,13,1,4,5,6,9,7,8,0,12" />
		  <Layer ID="24" Values="14,16,13,4,1,5,9,7,12,6,8,0" />
		  <Layer ID="25" Values="14,16,13,4,1,5,9,7,12,6,8,0" />
		  <Layer ID="26" Values="14,16,13,4,1,5,9,7,12,6,8,0" />
		  <Layer ID="27" Values="14,16,13,4,1,5,9,7,12,6,8,0" />
		  <Layer ID="28" Values="14,16,13,4,1,5,9,7,12,6,8,0" />
		  <Layer ID="29" Values="14,16,13,4,1,5,9,7,12,6,8,0" />
		  <Layer ID="30" Values="14,16,13,4,1,5,9,7,12,6,8,0" />
		  <Layer ID="31" Values="14,16,13,4,1,9,5,7,12,6,8,0" />
		  <Layer ID="16" Values="14,16,13,4,1,9,5,7,12,6,8,0" />
		  <Layer ID="41" Values="9,7,12,13,14,5,16,4,1,0,6,8" />
		  <Layer ID="42" Values="9,7,12,13,14,5,16,4,1,0,6,8" />
		  <Layer ID="40" Values="9,7,12,13,14,5,16,4,1,0,6,8" />
		  <Layer ID="43" Values="9,7,12,13,14,5,16,4,1,0,6,8" />
		  <Layer ID="44" Values="9,7,12,13,14,5,16,4,1,0,6,8" />
		  <Layer ID="45" Values="9,7,12,13,14,5,16,4,1,0,6,8" />
		  <Layer ID="64" Values="9,12,13,6,5,7,8,14,16,4,0,1" />
		  <Layer ID="65" Values="9,12,13,8,6,5,7,14,16,4,0,1" />
		</Layers>
		<Dirs>
		  <Dir ID="4" Values="9,12,13,6,5,8,7,14,16,4,0,1" />
		  <Dir ID="5" Values="8,6,12,13,5,14,16,4,9,7,0,1" />
		  <Dir ID="6" Values="8,6,12,13,14,5,16,4,9,0,7,1" />
		  <Dir ID="0" Values="14,16,13,1,4,5,6,7,8,9,0,12" />
		  <Dir ID="1" Values="14,16,13,4,1,5,7,12,6,8,0,9" />
		  <Dir ID="2" Values="7,12,13,14,5,16,4,1,0,6,8,9" />
		  <Dir ID="7" Values="14,16,13,4,1,8,6,5,12,0,7,9" />
		</Dirs>
	  </Action>
	  <Action Name="FreeStand3">
		<Layers />
		<Dirs>
		  <Dir ID="7" Values="14,16,13,4,1,8,6,5,12,0,7,9" />
		  <Dir ID="0" Values="14,16,13,1,4,7,5,9,6,12,8,0" />
		  <Dir ID="4" Values="12,13,8,6,5,14,16,4,1,0,9,7" />
		</Dirs>
	  </Action>
	  <Action Name="FreeStand2">
		<Layers />
		<Dirs>
		  <Dir ID="5" Values="8,6,12,13,5,14,16,4,1,0,7,9" />
		  <Dir ID="0" Values="14,16,13,1,4,9,7,5,8,6,12,0" />
		  <Dir ID="1" Values="14,16,13,9,7,4,1,5,12,8,6,0" />
		  <Dir ID="2" Values="9,7,12,13,14,5,16,4,1,0,8,6" />
		</Dirs>
	  </Action>
	  <Action Name="MeleeWPuncture">
		<Layers>
		  <Layer ID="86" Values="8,6,12,13,5,14,16,4,1,0,7,9" />
		  <Layer ID="72" Values="12,13,9,8,6,5,14,16,4,1,0,7" />
		  <Layer ID="73" Values="12,13,9,8,6,5,14,16,4,1,0,7" />
		  <Layer ID="74" Values="12,13,9,8,6,5,14,16,4,1,0,7" />
		</Layers>
		<Dirs>
		  <Dir ID="0" Values="14,16,13,1,4,7,5,6,8,0,12,9" />
		</Dirs>
	  </Action>
	  <Action Name="MeleeWCut">
		<Layers>
		  <Layer ID="7" Values="14,16,13,1,4,8,6,5,0,9,7,12" />
		  <Layer ID="8" Values="14,16,13,1,4,8,6,5,0,9,7,12" />
		  <Layer ID="9" Values="14,16,13,1,4,8,6,5,9,0,12,7" />
		  <Layer ID="6" Values="14,16,13,1,4,7,5,6,8,0,9,12" />
		  <Layer ID="5" Values="14,16,13,1,4,7,5,6,9,8,0,12" />
		  <Layer ID="10" Values="14,16,13,1,4,8,6,5,9,0,7,12" />
		  <Layer ID="11" Values="14,16,13,1,4,6,5,8,7,0,9,12" />
		  <Layer ID="12" Values="14,16,13,1,4,9,7,6,5,8,0,12" />
		  <Layer ID="13" Values="14,16,13,1,4,9,7,6,5,8,0,12" />
		  <Layer ID="64" Values="12,13,7,8,5,9,6,14,16,4,1,0" />
		  <Layer ID="65" Values="7,9,12,13,8,5,6,14,16,4,1,0" />
		  <Layer ID="66" Values="12,7,13,8,5,6,9,14,16,4,1,0" />
		  <Layer ID="63" Values="12,7,13,8,5,6,9,14,16,4,1,0" />
		  <Layer ID="62" Values="9,12,13,8,6,5,14,16,4,1,0,7" />
		  <Layer ID="67" Values="9,7,12,13,8,6,5,14,16,4,1,0" />
		</Layers>
		<Dirs />
	  </Action>
	  <Action Name="MeleeWDie">
		<Layers>
		  <Layer ID="6" Values="14,13,4,9,7,5,6,1,8,0,12,16" />
		  <Layer ID="7" Values="14,13,4,9,7,5,6,1,8,0,12,16" />
		  <Layer ID="8" Values="14,13,4,9,7,5,6,1,8,0,12,16" />
		  <Layer ID="9" Values="14,13,4,9,7,5,6,1,8,0,12,16" />
		  <Layer ID="10" Values="14,13,4,9,7,5,6,1,8,0,12,16" />
		  <Layer ID="11" Values="14,13,4,9,7,5,6,1,8,0,12,16" />
		  <Layer ID="12" Values="14,13,4,9,7,5,6,1,8,0,12,16" />
		  <Layer ID="13" Values="14,13,4,9,7,5,6,1,8,0,12,16" />
		  <Layer ID="14" Values="14,13,4,9,7,5,6,1,8,0,12,16" />
		  <Layer ID="15" Values="14,13,4,9,7,5,6,1,8,0,12,16" />
		  <Layer ID="16" Values="14,13,4,9,7,5,6,1,8,0,12,16" />
		  <Layer ID="17" Values="14,13,4,9,7,5,6,1,8,0,12,16" />
		  <Layer ID="18" Values="14,13,4,9,7,5,6,1,8,0,12,16" />
		  <Layer ID="19" Values="14,13,4,9,7,5,6,1,8,0,12,16" />
		  <Layer ID="83" Values="14,13,4,1,8,6,5,12,0,9,7,16" />
		  <Layer ID="84" Values="14,13,4,1,8,6,5,12,0,9,7,16" />
		  <Layer ID="85" Values="14,13,4,1,8,6,5,12,0,9,7,16" />
		  <Layer ID="86" Values="14,13,4,1,8,6,5,12,0,9,7,16" />
		  <Layer ID="87" Values="14,13,4,1,8,6,5,12,0,9,7,16" />
		  <Layer ID="88" Values="14,13,4,1,8,6,5,12,0,9,7,16" />
		  <Layer ID="89" Values="14,13,4,1,8,6,5,12,0,9,7,16" />
		  <Layer ID="90" Values="14,13,4,1,8,6,5,12,0,9,7,16" />
		  <Layer ID="91" Values="14,13,4,1,8,6,5,12,0,9,7,16" />
		  <Layer ID="92" Values="14,13,4,1,8,6,5,12,0,9,7,16" />
		  <Layer ID="93" Values="14,13,4,1,8,6,5,12,0,9,7,16" />
		  <Layer ID="94" Values="14,13,4,1,8,6,5,12,0,9,7,16" />
		  <Layer ID="95" Values="14,13,4,1,8,6,5,12,0,9,7,16" />
		  <Layer ID="96" Values="14,13,4,1,8,6,5,12,0,9,7,16" />
		</Layers>
		<Dirs>
		  <Dir ID="1" Values="14,13,9,7,4,1,5,12,6,8,0,16" />
		  <Dir ID="2" Values="9,7,12,13,14,5,4,1,0,6,8,16" />
		  <Dir ID="3" Values="9,7,0,12,13,5,14,4,1,8,6,16" />
		  <Dir ID="4" Values="12,13,8,0,6,5,14,16,4,1,7,9" />
		  <Dir ID="5" Values="0,8,6,12,13,5,14,16,4,1,9,7" />
		  <Dir ID="6" Values="8,6,12,13,14,5,4,1,0,9,7,16" />
		</Dirs>
	  </Action>
	  <Action Name="MeleeWWound">
		<Layers />
		<Dirs>
		  <Dir ID="6" Values="8,6,1,12,13,14,5,16,4,0,9,7" />
		</Dirs>
	  </Action>
	  <Action Name="FreeWound">
		<Layers />
		<Dirs>
		  <Dir ID="0" Values="14,16,13,1,4,7,5,9,6,12,8,0" />
		</Dirs>
	  </Action>
	  <Action Name="FreeDie">
		<Layers>
		  <Layer ID="31" Values="16,9,7,12,13,14,5,4,1,0,6,8" />
		  <Layer ID="32" Values="16,9,7,12,13,14,5,4,1,0,6,8" />
		  <Layer ID="33" Values="16,9,7,12,13,14,5,4,1,0,6,8" />
		  <Layer ID="34" Values="16,9,7,12,13,14,5,4,1,0,6,8" />
		  <Layer ID="35" Values="16,9,7,12,13,14,5,4,1,0,6,8" />
		  <Layer ID="43" Values="16,9,7,12,13,5,14,4,1,0,8,6" />
		  <Layer ID="44" Values="16,9,7,12,13,5,14,4,1,0,8,6" />
		  <Layer ID="45" Values="16,9,7,12,13,5,14,4,1,0,8,6" />
		  <Layer ID="46" Values="16,9,7,12,13,5,14,4,1,0,8,6" />
		  <Layer ID="47" Values="16,9,7,12,13,5,14,4,1,0,8,6" />
		  <Layer ID="55" Values="16,12,13,8,6,5,14,4,1,0,7,9" />
		  <Layer ID="56" Values="16,12,13,8,6,5,14,4,1,0,7,9" />
		  <Layer ID="57" Values="16,12,13,8,6,5,14,4,1,0,7,9" />
		  <Layer ID="58" Values="16,12,13,8,6,5,14,4,1,0,7,9" />
		  <Layer ID="59" Values="16,12,13,8,6,5,14,4,1,0,7,9" />
		  <Layer ID="67" Values="16,8,6,12,13,5,14,4,1,0,9,7" />
		  <Layer ID="68" Values="16,8,6,12,13,5,14,4,1,0,9,7" />
		  <Layer ID="69" Values="16,8,6,12,13,5,14,4,1,0,9,7" />
		  <Layer ID="70" Values="16,8,6,12,13,5,14,4,1,0,9,7" />
		  <Layer ID="71" Values="16,8,6,12,13,5,14,4,1,0,9,7" />
		</Layers>
		<Dirs>
		  <Dir ID="0" Values="14,16,13,1,4,7,5,9,6,12,8,0" />
		  <Dir ID="6" Values="16,8,6,12,13,14,4,1,5,0,9,7" />
		</Dirs>
	  </Action>
	  <Action Name="FreeAttack">
		<Layers>
		  <Layer ID="6" Values="14,16,13,1,4,6,5,7,9,12,8,0" />
		  <Layer ID="7" Values="14,16,13,1,4,6,5,7,9,12,8,0" />
		  <Layer ID="8" Values="14,16,13,1,4,6,5,7,9,12,8,0" />
		  <Layer ID="9" Values="14,16,13,1,4,6,5,7,9,12,8,0" />
		  <Layer ID="10" Values="14,16,13,1,4,6,5,7,9,12,8,0" />
		  <Layer ID="11" Values="14,16,13,1,4,6,5,7,9,12,8,0" />
		  <Layer ID="12" Values="14,16,13,1,4,6,5,7,9,12,8,0" />
		  <Layer ID="13" Values="14,16,13,1,4,6,5,7,9,12,8,0" />
		  <Layer ID="68" Values="9,7,12,13,6,8,5,14,16,4,1,0" />
		  <Layer ID="69" Values="9,7,12,13,8,6,5,14,16,4,1,0" />
		  <Layer ID="70" Values="9,7,12,13,8,6,5,14,16,4,1,0" />
		  <Layer ID="71" Values="9,7,12,13,8,6,5,14,16,4,1,0" />
		  <Layer ID="78" Values="12,13,8,9,7,5,6,14,16,4,1,0" />
		  <Layer ID="79" Values="12,13,8,7,9,5,6,14,16,4,1,0" />
		  <Layer ID="80" Values="12,13,8,9,7,5,6,14,16,4,1,0" />
		  <Layer ID="81" Values="12,13,8,9,7,5,6,14,16,4,1,0" />
		  <Layer ID="82" Values="12,13,8,9,7,5,6,14,16,4,1,0" />
		  <Layer ID="83" Values="12,13,8,7,9,5,6,14,16,4,1,0" />
		  <Layer ID="84" Values="12,13,8,9,7,5,6,14,16,4,1,0" />
		  <Layer ID="85" Values="12,13,8,9,7,5,6,14,16,4,1,0" />
		  <Layer ID="140" Values="14,16,13,4,1,5,6,12,0,7,9,8" />
		  <Layer ID="141" Values="14,16,13,4,1,5,6,8,12,0,7,9" />
		  <Layer ID="142" Values="14,16,13,4,1,5,6,8,12,0,7,9" />
		  <Layer ID="143" Values="14,16,13,4,1,6,5,8,12,0,7,9" />
		</Layers>
		<Dirs>
		  <Dir ID="0" Values="14,16,13,1,4,7,5,9,6,12,8,0" />
		  <Dir ID="7" Values="14,16,13,4,1,8,6,5,12,0,7,9" />
		</Dirs>
	  </Action>
	  <Action Name="FreeMagic">
		<Layers>
		  <Layer ID="6" Values="14,16,13,1,4,5,7,9,6,12,8,0" />
		  <Layer ID="7" Values="14,16,13,1,4,5,7,9,6,12,8,0" />
		  <Layer ID="8" Values="14,16,13,1,4,5,7,9,6,12,8,0" />
		  <Layer ID="9" Values="14,16,13,1,4,5,7,9,6,12,8,0" />
		  <Layer ID="54" Values="12,13,8,6,9,7,5,14,16,4,1,0" />
		  <Layer ID="55" Values="12,13,8,6,9,7,5,14,16,4,1,0" />
		  <Layer ID="56" Values="12,13,8,6,9,7,5,14,16,4,1,0" />
		  <Layer ID="57" Values="12,13,8,6,7,9,5,14,16,4,1,0" />
		  <Layer ID="58" Values="12,13,8,6,9,7,5,14,16,4,1,0" />
		</Layers>
		<Dirs>
		  <Dir ID="0" Values="14,16,13,1,4,7,5,6,12,8,0,9" />
		  <Dir ID="3" Values="9,7,12,13,8,6,5,14,16,4,1,0" />
		  <Dir ID="7" Values="14,16,13,4,1,8,6,5,12,0,7,9" />
		</Dirs>
	  </Action>
	  <Action Name="JumpFly">
		<Layers />
		<Dirs>
		  <Dir ID="6" Values="6,8,12,13,14,5,16,4,1,0,9,7" />
		  <Dir ID="7" Values="14,16,13,4,1,6,8,5,12,0,7,9" />
		  <Dir ID="0" Values="14,16,13,1,4,7,9,5,6,12,8,0" />
		</Dirs>
	  </Action>
	  <Action Name="DartThrow">
		<Layers>
		  <Layer ID="11" Values="14,16,13,1,4,6,8,5,7,9,12,0" />
		  <Layer ID="12" Values="14,16,13,1,4,6,5,9,7,12,8,0" />
		  <Layer ID="13" Values="14,16,13,1,4,6,5,7,9,12,8,0" />
		  <Layer ID="68" Values="12,13,8,6,9,7,5,14,16,4,1,0" />
		  <Layer ID="69" Values="12,13,8,6,9,7,5,14,16,4,1,0" />
		  <Layer ID="70" Values="12,13,8,6,9,7,5,14,16,4,1,0" />
		  <Layer ID="74" Values="12,13,8,9,7,6,5,14,16,4,1,0" />
		  <Layer ID="75" Values="12,13,8,9,7,5,6,14,16,4,1,0" />
		</Layers>
		<Dirs>
		  <Dir ID="0" Values="14,16,13,1,4,7,9,5,6,12,8,0" />
		  <Dir ID="7" Values="14,16,13,4,1,8,6,5,12,0,7,9" />
		</Dirs>
	  </Action>
	  <Action Name="MeleeWRun">
		<Layers />
		<Dirs>
		  <Dir ID="0" Values="14,16,13,1,4,9,7,6,5,12,8,0" />
		</Dirs>
	  </Action>
	  <Action Name="FreeStand1">
		<Layers />
		<Dirs>
		  <Dir ID="0" Values="14,16,13,1,4,9,7,5,8,6,12,0" />
		  <Dir ID="1" Values="14,16,13,9,7,4,1,5,12,8,6,0" />
		  <Dir ID="2" Values="9,7,12,13,14,5,16,4,1,0,8,6" />
		</Dirs>
	  </Action>
	  <Action Name="SitDown">
		<Layers>
		  <Layer ID="8" Values="14,16,13,1,4,7,5,6,12,0,8,9" />
		  <Layer ID="17" Values="14,16,13,7,4,1,5,12,6,0,9,8" />
		</Layers>
		<Dirs>
		  <Dir ID="4" Values="12,13,8,6,5,14,16,4,1,0,9,7" />
		</Dirs>
	  </Action>
	</Male>

	<Female>
	  <Action Name="DEFAULT">
		<Layers />
		<Dirs>
		  <Dir ID="0" Values="14,16,13,1,4,9,7,5,6,12,8,0" />
		  <Dir ID="1" Values="14,16,13,9,7,4,1,5,12,6,8,0" />
		  <Dir ID="2" Values="9,7,12,13,14,5,16,4,1,0,6,8" />
		  <Dir ID="3" Values="9,7,12,13,5,14,16,4,1,0,8,6" />
		  <Dir ID="4" Values="12,13,8,6,5,14,16,4,1,0,7,9" />
		  <Dir ID="5" Values="8,6,12,13,5,14,16,4,1,0,9,7" />
		  <Dir ID="6" Values="8,6,12,13,14,5,16,4,1,0,9,7" />
		  <Dir ID="7" Values="14,16,13,4,1,8,6,5,12,0,9,7" />
		  <Dir ID="8" Values="12,13,14,8,6,9,5,16,4,0,1,7" />
		  <Dir ID="9" Values="12,13,14,8,6,9,5,16,4,0,1,7" />
		  <Dir ID="10" Values="12,13,14,8,6,9,5,16,4,0,1,7" />
		  <Dir ID="11" Values="12,13,14,8,6,5,16,4,0,1,9,7" />
		  <Dir ID="12" Values="12,13,14,8,6,5,16,4,0,1,9,7" />
		  <Dir ID="13" Values="12,13,14,8,6,5,16,4,1,0,7,9" />
		  <Dir ID="14" Values="12,13,14,6,8,5,16,4,1,0,7,9" />
		  <Dir ID="15" Values="12,13,14,5,16,0,1,6,8,7,9,4" />
		</Dirs>
	  </Action>
	  <Action Name="RangeWStand">
		<Layers />
		<Dirs>
		  <Dir ID="0" Values="14,16,13,1,4,7,5,6,9,8,0,12" />
		  <Dir ID="1" Values="14,16,13,7,4,1,5,12,6,8,0,9" />
		  <Dir ID="4" Values="12,13,9,8,6,7,5,14,16,4,1,0" />
		  <Dir ID="5" Values="8,6,12,13,9,5,14,16,4,1,0,7" />
		</Dirs>
	  </Action>
	  <Action Name="RangeWWound">
		<Layers>
		  <Layer ID="12" Values="9,7,12,13,14,5,16,4,1,0,6,8" />
		</Layers>
		<Dirs>
		  <Dir ID="0" Values="14,16,13,1,4,7,6,5,12,8,0,9" />
		  <Dir ID="1" Values="14,16,13,7,4,1,5,12,6,8,0,9" />
		  <Dir ID="2" Values="7,12,13,14,5,16,4,1,0,6,8,9" />
		  <Dir ID="4" Values="9,12,13,8,6,7,5,14,16,4,1,0" />
		  <Dir ID="5" Values="9,8,6,12,13,5,14,16,4,1,0,7" />
		  <Dir ID="6" Values="8,6,12,13,14,5,16,4,1,9,7,0" />
		</Dirs>
	  </Action>
	  <Action Name="RangeWDie">
		<Layers>
		  <Layer ID="20" Values="9,7,12,13,14,5,16,4,1,0,6,8" />
		  <Layer ID="21" Values="9,7,12,13,14,5,16,4,1,0,6,8" />
		  <Layer ID="22" Values="9,7,12,13,14,5,16,4,1,0,6,8" />
		  <Layer ID="36" Values="7,12,13,5,14,16,4,1,0,8,6,9" />
		  <Layer ID="37" Values="7,12,13,5,14,16,4,1,0,8,6,9" />
		  <Layer ID="38" Values="7,12,13,5,14,16,4,1,0,8,6,9" />
		  <Layer ID="39" Values="7,12,13,5,14,16,4,1,0,8,6,9" />
		  <Layer ID="40" Values="9,12,13,8,6,5,14,16,4,1,0,7" />
		  <Layer ID="41" Values="9,12,13,8,6,5,14,16,4,1,0,7" />
		  <Layer ID="50" Values="9,8,6,12,13,5,14,16,4,1,0,7" />
		</Layers>
		<Dirs>
		  <Dir ID="0" Values="14,16,13,1,4,7,5,6,12,8,0,9" />
		  <Dir ID="1" Values="14,16,13,7,4,1,5,12,6,8,0,9" />
		  <Dir ID="2" Values="7,12,13,14,5,16,4,1,0,6,8,9" />
		</Dirs>
	  </Action>
	  <Action Name="RangeWMagic">
		<Layers />
		<Dirs>
		  <Dir ID="0" Values="14,16,13,1,4,7,5,6,12,8,0,9" />
		  <Dir ID="1" Values="14,16,13,7,4,1,5,12,6,8,0,9" />
		  <Dir ID="4" Values="9,12,13,8,6,7,5,14,16,4,1,0" />
		  <Dir ID="5" Values="9,8,6,12,13,5,14,16,4,1,0,7" />
		</Dirs>
	  </Action>
	  <Action Name="RangeWCut">
		<Layers>
		  <Layer ID="2" Values="14,16,13,1,4,6,5,7,12,8,0,9" />
		  <Layer ID="1" Values="14,16,13,1,4,6,5,7,12,8,0,9" />
		  <Layer ID="3" Values="14,16,13,1,4,6,5,7,12,8,0,9" />
		  <Layer ID="4" Values="14,16,13,1,4,6,5,7,12,8,0,9" />
		  <Layer ID="5" Values="14,16,13,1,4,6,5,7,12,8,0,9" />
		  <Layer ID="12" Values="14,16,13,7,4,1,5,12,6,8,0,9" />
		  <Layer ID="13" Values="14,16,13,7,4,1,5,12,6,8,0,9" />
		  <Layer ID="14" Values="14,16,13,4,1,6,5,7,12,8,0,9" />
		  <Layer ID="15" Values="14,16,13,4,1,6,5,7,12,8,0,9" />
		  <Layer ID="16" Values="14,16,13,4,1,6,5,7,12,8,0,9" />
		  <Layer ID="17" Values="14,16,13,4,1,6,5,7,12,8,0,9" />
		  <Layer ID="18" Values="14,16,13,7,4,1,5,12,6,8,0,9" />
		  <Layer ID="25" Values="7,12,13,14,5,16,4,1,0,6,8,9" />
		  <Layer ID="26" Values="7,12,13,14,5,16,4,1,0,6,8,9" />
		  <Layer ID="27" Values="7,12,13,14,5,16,4,1,0,6,8,9" />
		  <Layer ID="28" Values="7,12,13,14,5,16,4,1,0,6,8,9" />
		  <Layer ID="29" Values="7,12,13,14,5,16,4,1,0,6,8,9" />
		  <Layer ID="30" Values="7,12,13,14,5,16,4,1,9,0,6,8" />
		  <Layer ID="38" Values="7,12,13,5,14,16,4,1,0,8,6,9" />
		  <Layer ID="39" Values="7,12,13,5,14,16,4,1,0,8,6,9" />
		  <Layer ID="40" Values="7,12,13,5,14,16,4,1,0,8,6,9" />
		  <Layer ID="41" Values="7,12,13,5,14,16,4,1,0,8,6,9" />
		  <Layer ID="43" Values="9,12,13,6,5,14,16,7,4,1,0,8" />
		  <Layer ID="44" Values="9,12,13,6,5,7,14,16,4,1,0,8" />
		  <Layer ID="45" Values="9,12,13,6,5,7,14,16,4,1,0,8" />
		  <Layer ID="46" Values="9,12,13,6,5,7,14,16,4,1,0,8" />
		  <Layer ID="52" Values="12,13,8,7,5,6,14,16,4,1,0,9" />
		  <Layer ID="50" Values="9,12,13,8,7,5,6,14,16,4,1,0" />
		  <Layer ID="51" Values="9,12,13,8,7,5,6,14,16,4,1,0" />
		  <Layer ID="53" Values="9,12,13,8,7,5,6,14,16,4,1,0" />
		  <Layer ID="64" Values="9,8,12,13,7,5,6,14,16,4,1,0" />
		  <Layer ID="63" Values="9,8,12,13,7,5,6,14,16,4,1,0" />
		  <Layer ID="65" Values="9,8,12,13,7,5,6,14,16,4,1,0" />
		  <Layer ID="67" Values="8,6,12,13,5,9,14,16,4,1,0,7" />
		  <Layer ID="68" Values="8,6,12,13,5,14,16,4,1,0,7,9" />
		  <Layer ID="69" Values="8,6,12,13,5,14,16,4,1,0,7,9" />
		  <Layer ID="70" Values="8,6,12,13,5,14,16,4,1,0,7,9" />
		  <Layer ID="74" Values="9,8,6,12,13,14,5,16,4,1,7,0" />
		  <Layer ID="75" Values="9,8,6,12,13,14,5,16,4,1,7,0" />
		  <Layer ID="76" Values="9,8,6,12,13,14,5,16,4,1,7,0" />
		  <Layer ID="77" Values="9,8,6,12,13,14,5,16,4,1,7,0" />
		  <Layer ID="87" Values="9,14,16,13,4,1,8,6,5,12,0,7" />
		  <Layer ID="88" Values="9,14,16,13,4,1,8,6,5,12,0,7" />
		  <Layer ID="89" Values="9,14,16,13,4,1,8,6,5,12,0,7" />
		  <Layer ID="91" Values="14,16,13,4,1,8,5,6,12,0,9,7" />
		  <Layer ID="92" Values="14,16,13,4,1,8,5,6,12,0,9,7" />
		  <Layer ID="93" Values="14,16,13,4,1,8,5,6,12,0,9,7" />
		  <Layer ID="94" Values="14,16,13,4,1,8,5,6,12,0,9,7" />
		  <Layer ID="0" Values="14,16,13,1,4,7,6,5,12,8,0,9" />
		  <Layer ID="62" Values="9,8,6,12,13,7,5,14,16,4,1,0" />
		</Layers>
		<Dirs>
		  <Dir ID="0" Values="14,16,13,1,4,7,5,6,12,8,0,9" />
		  <Dir ID="4" Values="9,12,13,8,6,5,14,16,4,1,0,7" />
		  <Dir ID="5" Values="9,8,6,12,13,5,14,16,4,1,0,7" />
		  <Dir ID="6" Values="8,6,12,13,14,5,16,4,1,9,7,0" />
		</Dirs>
	  </Action>
	  <Action Name="RangeWPuncture">
		<Layers>
		  <Layer ID="13" Values="14,16,13,7,4,1,5,12,6,8,0,9" />
		  <Layer ID="14" Values="14,16,13,7,4,1,5,12,6,8,0,9" />
		  <Layer ID="25" Values="14,16,13,7,4,1,5,12,6,8,0,9" />
		  <Layer ID="43" Values="9,7,12,13,6,5,14,16,4,1,0,8" />
		  <Layer ID="44" Values="9,7,12,13,6,5,14,16,4,1,0,8" />
		  <Layer ID="45" Values="9,7,12,13,6,5,14,16,4,1,0,8" />
		  <Layer ID="6" Values="14,16,13,1,4,5,7,6,12,8,0,9" />
		  <Layer ID="7" Values="14,16,13,1,4,5,7,6,12,8,0,9" />
		  <Layer ID="8" Values="14,16,13,1,4,5,7,6,12,8,0,9" />
		  <Layer ID="42" Values="9,7,12,13,6,5,14,16,4,1,0,8" />
		  <Layer ID="59" Values="9,12,13,8,6,7,5,14,16,4,1,0" />
		  <Layer ID="60" Values="9,12,13,8,6,7,5,14,16,4,1,0" />
		  <Layer ID="82" Values="8,12,13,14,5,16,6,4,1,0,9,7" />
		  <Layer ID="83" Values="8,12,13,14,5,16,6,4,1,0,9,7" />
		  <Layer ID="93" Values="14,16,13,4,1,8,5,6,12,0,9,7" />
		  <Layer ID="94" Values="14,16,13,4,1,8,5,6,12,0,9,7" />
		  <Layer ID="95" Values="14,16,13,4,1,8,5,6,12,0,9,7" />
		  <Layer ID="96" Values="14,16,13,4,1,8,5,6,12,0,9,7" />
		  <Layer ID="97" Values="14,16,13,4,1,8,5,6,12,0,9,7" />
		  <Layer ID="100" Values="14,16,13,4,1,8,5,6,12,0,9,7" />
		  <Layer ID="101" Values="14,16,13,4,1,8,5,6,12,0,9,7" />
		</Layers>
		<Dirs>
		  <Dir ID="0" Values="14,16,13,1,4,7,5,6,12,8,0,9" />
		  <Dir ID="4" Values="9,12,13,8,6,5,14,16,4,1,0,7" />
		  <Dir ID="5" Values="8,6,12,13,5,14,16,4,1,9,7,0" />
		</Dirs>
	  </Action>
	  <Action Name="RideStand">
		<Layers />
		<Dirs>
		  <Dir ID="4" Values="12,13,8,6,5,14,16,0,7,9,4,1" />
		  <Dir ID="0" Values="14,16,13,1,4,9,7,6,5,12,8,0" />
		  <Dir ID="3" Values="9,7,12,13,5,14,16,0,8,6,4,1" />
		</Dirs>
	  </Action>
	  <Action Name="RideStand1">
		<Layers />
		<Dirs>
		  <Dir ID="4" Values="12,13,8,6,5,14,16,0,7,9,4,1" />
		  <Dir ID="0" Values="14,16,13,1,4,9,7,6,5,12,8,0" />
		  <Dir ID="3" Values="9,7,12,13,5,14,16,0,8,6,4,1" />
		</Dirs>
	  </Action>
	  <Action Name="RideStand2">
		<Layers />
		<Dirs>
		  <Dir ID="4" Values="12,13,8,6,5,14,16,0,7,9,4,1" />
		  <Dir ID="0" Values="14,16,13,1,4,9,7,6,5,12,8,0" />
		  <Dir ID="3" Values="9,7,12,13,5,14,16,0,8,6,4,1" />
		</Dirs>
	  </Action>
	  <Action Name="RideRun">
		<Layers />
		<Dirs>
		  <Dir ID="4" Values="12,13,8,6,5,14,16,0,9,7,4,1" />
		  <Dir ID="0" Values="14,16,13,9,7,4,1,5,6,12,8,0" />
		  <Dir ID="3" Values="9,7,12,13,5,14,16,0,8,6,4,1" />
		</Dirs>
	  </Action>
	  <Action Name="RideWalk">
		<Layers />
		<Dirs>
		  <Dir ID="4" Values="12,13,8,6,5,14,16,0,7,9,4,1" />
		  <Dir ID="0" Values="14,16,13,1,4,9,7,6,5,12,8,0" />
		  <Dir ID="3" Values="9,7,12,13,5,14,16,0,8,6,4,1" />
		</Dirs>
	  </Action>
	  <Action Name="RideWound">
		<Layers>
		  <Layer ID="2" Values="14,16,13,1,4,9,7,8,6,5,12,0" />
		</Layers>
		<Dirs>
		  <Dir ID="4" Values="12,13,8,6,5,14,16,0,9,7,4,1" />
		  <Dir ID="0" Values="14,16,13,1,4,9,7,6,5,12,8,0" />
		  <Dir ID="3" Values="9,7,12,13,5,14,16,0,8,6,4,1" />
		</Dirs>
	  </Action>
	  <Action Name="RideMagic">
		<Layers>
		  <Layer ID="8" Values="14,16,13,1,4,7,5,12,8,0,9,6" />
		  <Layer ID="9" Values="14,16,13,1,4,7,5,12,8,0,9,6" />
		  <Layer ID="10" Values="14,16,13,1,4,7,5,12,8,0,9,6" />
		  <Layer ID="0" Values="14,16,13,1,4,9,7,6,5,12,8,0" />
		  <Layer ID="1" Values="14,16,13,1,4,9,7,6,5,12,8,0" />
		  <Layer ID="2" Values="14,16,13,1,4,9,7,6,5,12,8,0" />
		  <Layer ID="11" Values="14,16,13,1,4,9,7,6,5,12,8,0" />
		</Layers>
		<Dirs>
		  <Dir ID="0" Values="14,16,13,1,4,9,7,5,12,8,0,6" />
		  <Dir ID="4" Values="12,13,8,5,6,14,16,0,7,9,4,1" />
		  <Dir ID="3" Values="9,7,12,13,5,14,16,0,8,6,4,1" />
		</Dirs>
	  </Action>
	  <Action Name="RideDie">
		<Layers>
		  <Layer ID="6" Values="14,16,13,1,4,7,5,6,12,8,0,9" />
		  <Layer ID="7" Values="14,16,13,1,4,7,5,6,12,8,0,9" />
		  <Layer ID="8" Values="14,16,13,1,4,7,5,6,12,8,0,9" />
		  <Layer ID="9" Values="14,16,13,1,4,5,6,12,8,0,7,9" />
		  <Layer ID="10" Values="14,16,13,1,4,5,6,12,8,0,7,9" />
		  <Layer ID="11" Values="8,14,16,13,1,4,5,6,12,0,7,9" />
		  <Layer ID="13" Values="8,14,16,13,1,4,5,6,12,0,7,9" />
		  <Layer ID="12" Values="8,14,16,13,1,4,5,6,12,0,7,9" />
		  <Layer ID="23" Values="14,16,13,4,1,5,12,6,8,0,7,9" />
		  <Layer ID="24" Values="14,16,13,4,1,5,12,6,8,0,7,9" />
		  <Layer ID="25" Values="14,16,13,4,1,5,12,6,8,0,7,9" />
		  <Layer ID="26" Values="14,16,13,4,1,5,12,6,8,0,9,7" />
		  <Layer ID="27" Values="14,16,13,4,1,5,12,6,8,0,9,7" />
		  <Layer ID="37" Values="6,12,13,14,5,16,4,1,0,8,7,9" />
		  <Layer ID="38" Values="6,12,13,14,5,16,4,1,0,8,7,9" />
		  <Layer ID="39" Values="6,12,13,14,5,16,4,1,0,8,7,9" />
		  <Layer ID="40" Values="6,12,13,14,5,16,4,1,0,8,7,9" />
		  <Layer ID="41" Values="6,12,13,14,5,16,4,1,0,8,7,9" />
		  <Layer ID="51" Values="6,12,13,5,14,16,4,1,0,8,7,9" />
		  <Layer ID="52" Values="6,12,13,5,14,16,4,1,0,8,7,9" />
		  <Layer ID="53" Values="6,12,13,5,14,16,4,1,0,8,7,9" />
		  <Layer ID="54" Values="6,12,13,5,14,16,4,1,0,8,7,9" />
		  <Layer ID="55" Values="6,12,13,5,14,16,4,1,0,8,7,9" />
		</Layers>
		<Dirs>
		  <Dir ID="3" Values="9,7,12,13,5,14,16,0,8,6,4,1" />
		  <Dir ID="4" Values="12,13,8,6,5,14,16,0,7,9,4,1" />
		</Dirs>
	  </Action>
	  <Action Name="RideCut">
		<Layers>
		  <Layer ID="4" Values="14,16,13,1,4,7,5,6,12,8,0,9" />
		  <Layer ID="7" Values="14,16,13,1,4,7,9,5,6,12,8,0" />
		  <Layer ID="8" Values="14,16,13,1,4,5,7,12,8,6,0,9" />
		  <Layer ID="9" Values="14,16,13,1,4,5,7,12,9,8,6,0" />
		  <Layer ID="10" Values="14,16,13,1,4,5,12,8,6,0,9,7" />
		  <Layer ID="56" Values="12,13,5,8,6,14,16,9,7,4,0,1" />
		  <Layer ID="88" Values="14,16,13,4,1,8,6,5,12,0,7,9" />
		  <Layer ID="89" Values="14,16,13,4,1,8,6,5,12,0,7,9" />
		  <Layer ID="90" Values="14,16,13,4,1,8,6,5,12,0,7,9" />
		  <Layer ID="11" Values="14,16,13,1,4,9,7,5,12,8,6,0" />
		  <Layer ID="55" Values="12,13,5,8,6,14,16,9,0,7,4,1" />
		  <Layer ID="57" Values="9,12,13,5,6,8,14,16,7,4,0,1" />
		  <Layer ID="58" Values="12,13,5,6,8,14,16,0,9,7,4,1" />
		  <Layer ID="59" Values="12,13,5,8,6,14,16,0,9,7,4,1" />
		  <Layer ID="48" Values="12,13,8,5,6,14,16,0,9,7,4,1" />
		  <Layer ID="53" Values="12,13,8,6,5,14,16,0,7,4,1,9" />
		  <Layer ID="54" Values="12,13,8,6,5,14,16,0,7,4,1,9" />
		</Layers>
		<Dirs>
		  <Dir ID="4" Values="12,13,8,6,5,14,16,0,9,7,4,1" />
		  <Dir ID="3" Values="9,7,12,13,5,14,16,0,8,6,4,1" />
		</Dirs>
	  </Action>
	  <Action Name="RidePuncture">
		<Layers>
		  <Layer ID="5" Values="14,16,13,1,4,5,12,8,6,0,9,7" />
		  <Layer ID="6" Values="14,16,13,1,4,5,6,12,8,0,9,7" />
		  <Layer ID="10" Values="14,16,13,1,4,7,5,12,8,6,0,9" />
		  <Layer ID="11" Values="14,16,13,1,4,5,12,8,6,0,9,7" />
		  <Layer ID="12" Values="14,16,13,1,4,5,12,8,6,0,9,7" />
		  <Layer ID="13" Values="14,16,13,1,4,9,7,5,12,8,6,0" />
		  <Layer ID="61" Values="12,13,9,5,8,6,14,16,0,7,4,1" />
		  <Layer ID="62" Values="12,13,9,5,8,6,14,16,0,7,4,1" />
		  <Layer ID="66" Values="9,12,13,5,8,6,14,16,0,7,4,1" />
		  <Layer ID="67" Values="9,12,13,5,8,6,14,16,0,7,4,1" />
		  <Layer ID="68" Values="9,12,13,5,8,6,14,16,7,4,0,1" />
		</Layers>
		<Dirs>
		  <Dir ID="1" Values="14,16,13,9,7,4,1,5,12,8,6,0" />
		  <Dir ID="4" Values="12,13,8,6,5,14,16,0,9,7,4,1" />
		  <Dir ID="3" Values="9,7,12,13,5,14,16,0,8,6,4,1" />
		</Dirs>
	  </Action>
	  <Action Name="FreeWalk">
		<Layers>
		  <Layer ID="8" Values="14,16,13,1,4,5,7,6,8,0,9,12" />
		  <Layer ID="9" Values="14,16,13,1,4,5,7,9,6,8,0,12" />
		  <Layer ID="10" Values="14,16,13,1,4,5,7,6,8,9,0,12" />
		</Layers>
		<Dirs>
		  <Dir ID="4" Values="12,13,8,6,5,14,16,4,1,0,9,7" />
		</Dirs>
	  </Action>
	  <Action Name="FreeRun">
		<Layers>
		  <Layer ID="0" Values="14,16,13,1,4,6,5,7,9,8,0,12" />
		  <Layer ID="1" Values="14,16,13,1,4,6,5,7,9,8,0,12" />
		  <Layer ID="3" Values="14,16,13,1,4,7,5,9,6,8,0,12" />
		  <Layer ID="4" Values="14,16,13,1,4,7,5,9,6,8,0,12" />
		  <Layer ID="5" Values="14,16,13,1,4,7,5,9,6,8,0,12" />
		  <Layer ID="6" Values="14,16,13,1,4,7,5,9,6,8,0,12" />
		  <Layer ID="7" Values="14,16,13,1,4,7,5,9,6,8,0,12" />
		  <Layer ID="8" Values="14,16,13,1,4,7,5,9,6,8,0,12" />
		  <Layer ID="44" Values="12,13,8,9,7,5,6,14,16,4,1,0" />
		  <Layer ID="52" Values="12,13,6,8,9,7,5,14,16,0,4,1" />
		</Layers>
		<Dirs>
		  <Dir ID="0" Values="14,16,13,1,4,5,7,9,6,8,0,12" />
		  <Dir ID="1" Values="14,16,13,7,9,4,1,5,12,6,8,0" />
		  <Dir ID="4" Values="12,13,8,6,9,7,5,14,16,0,4,1" />
		  <Dir ID="7" Values="14,16,13,4,1,8,6,5,12,0,7,9" />
		</Dirs>
	  </Action>
	  <Action Name="DoubleWDie">
		<Layers>
		  <Layer ID="1" Values="14,16,13,1,4,6,5,7,8,0,12,9" />
		  <Layer ID="8" Values="14,16,13,5,7,6,8,0,12,9,4,1" />
		  <Layer ID="9" Values="14,16,13,5,7,6,8,0,12,9,4,1" />
		  <Layer ID="15" Values="14,16,13,9,7,5,12,6,0,8,4,1" />
		  <Layer ID="16" Values="14,16,13,9,7,5,12,6,0,8,4,1" />
		  <Layer ID="17" Values="14,16,13,9,7,5,12,6,0,8,4,1" />
		  <Layer ID="18" Values="14,16,13,9,7,5,12,6,0,8,4,1" />
		  <Layer ID="19" Values="14,16,13,9,7,5,12,6,0,8,4,1" />
		</Layers>
		<Dirs>
		  <Dir ID="0" Values="14,16,13,1,4,5,7,6,8,0,12,9" />
		  <Dir ID="1" Values="14,16,13,9,7,4,1,5,12,6,0,8" />
		  <Dir ID="4" Values="12,13,8,6,9,5,14,16,4,1,0,7" />
		</Dirs>
	  </Action>
	  <Action Name="DoubleWStand">
		<Layers />
		<Dirs>
		  <Dir ID="0" Values="14,16,13,1,4,7,5,6,8,0,9,12" />
		</Dirs>
	  </Action>
	  <Action Name="DoubleWWound">
		<Layers>
		  <Layer ID="24" Values="12,13,8,6,5,14,16,4,9,1,0,7" />
		</Layers>
		<Dirs>
		  <Dir ID="0" Values="14,16,13,1,4,7,5,6,8,0,9,12" />
		  <Dir ID="1" Values="14,16,13,7,4,1,5,12,6,8,0,9" />
		  <Dir ID="4" Values="12,13,8,5,6,14,16,4,9,1,0,7" />
		</Dirs>
	  </Action>
	  <Action Name="DoubleWPound">
		<Layers>
		  <Layer ID="54" Values="12,13,6,8,5,14,16,4,1,0,7,9" />
		  <Layer ID="66" Values="8,6,12,13,5,14,16,4,1,0,7,9" />
		</Layers>
		<Dirs>
		  <Dir ID="0" Values="13,1,4,7,16,5,6,9,0,8,12,14" />
		  <Dir ID="7" Values="14,16,13,4,1,8,6,5,12,0,7,9" />
		  <Dir ID="4" Values="12,13,8,6,5,14,16,4,1,0,9,7" />
		  <Dir ID="6" Values="8,6,12,13,14,5,16,4,1,0,7,9" />
		</Dirs>
	  </Action>
	  <Action Name="DoubleWPull">
		<Layers>
		  <Layer ID="69" Values="12,13,9,8,7,5,6,14,16,4,1,0" />
		  <Layer ID="70" Values="12,13,9,8,7,5,6,14,16,4,1,0" />
		  <Layer ID="1" Values="14,16,13,1,4,7,5,6,8,0,9,12" />
		  <Layer ID="2" Values="14,16,13,1,4,7,5,6,8,0,9,12" />
		  <Layer ID="3" Values="14,16,13,1,4,7,5,6,8,0,9,12" />
		  <Layer ID="4" Values="14,16,13,1,4,7,5,6,8,0,9,12" />
		  <Layer ID="5" Values="14,16,13,1,4,6,5,7,8,0,9,12" />
		  <Layer ID="6" Values="14,16,13,1,4,6,5,7,8,0,9,12" />
		  <Layer ID="7" Values="14,16,13,1,4,6,5,7,8,0,9,12" />
		  <Layer ID="12" Values="14,16,13,1,4,7,5,6,8,0,9,12" />
		  <Layer ID="13" Values="14,16,13,1,4,7,5,6,8,0,9,12" />
		  <Layer ID="14" Values="14,16,13,1,4,7,5,6,8,0,9,12" />
		  <Layer ID="15" Values="14,16,13,1,4,7,5,6,8,0,9,12" />
		  <Layer ID="71" Values="12,13,8,9,7,5,6,14,16,4,1,0" />
		  <Layer ID="72" Values="12,13,8,9,7,5,6,14,16,4,1,0" />
		  <Layer ID="73" Values="12,13,8,9,7,5,6,14,16,4,1,0" />
		</Layers>
		<Dirs>
		  <Dir ID="0" Values="14,16,13,1,4,5,6,7,8,0,9,12" />
		  <Dir ID="4" Values="12,13,8,9,6,5,14,16,4,1,0,7" />
		  <Dir ID="7" Values="14,16,13,4,1,8,6,5,12,0,7,9" />
		</Dirs>
	  </Action>
	  <Action Name="DoubleWMagic">
		<Layers />
		<Dirs>
		  <Dir ID="0" Values="14,16,13,1,4,7,5,6,0,12,9,8" />
		  <Dir ID="7" Values="14,16,13,4,1,8,6,5,12,0,7,9" />
		</Dirs>
	  </Action>
	  <Action Name="MeleeWStand">
		<Layers />
		<Dirs>
		  <Dir ID="6" Values="8,6,12,13,14,4,1,5,16,0,9,7" />
		  <Dir ID="4" Values="12,13,8,6,5,14,16,4,1,0,9,7" />
		</Dirs>
	  </Action>
	  <Action Name="MeleeWCut">
		<Layers>
		  <Layer ID="62" Values="9,12,7,13,8,5,6,14,16,4,1,0" />
		  <Layer ID="60" Values="12,13,6,8,5,14,16,4,1,0,7,9" />
		  <Layer ID="61" Values="9,7,12,13,8,5,6,14,16,4,1,0" />
		  <Layer ID="8" Values="14,16,13,1,4,5,6,8,0,12,9,7" />
		  <Layer ID="9" Values="14,16,13,1,4,5,6,8,0,12,9,7" />
		  <Layer ID="10" Values="14,16,13,1,4,5,6,8,0,12,9,7" />
		  <Layer ID="11" Values="14,16,13,1,4,7,5,6,8,0,12,9" />
		</Layers>
		<Dirs />
	  </Action>
	  <Action Name="MeleeWPuncture">
		<Layers>
		  <Layer ID="58" Values="7,9,12,13,8,6,5,14,16,4,1,0" />
		  <Layer ID="6" Values="14,16,13,1,4,7,5,9,6,12,8,0" />
		  <Layer ID="7" Values="14,16,13,1,4,5,7,9,6,12,8,0" />
		  <Layer ID="8" Values="14,16,13,1,4,6,5,7,9,12,8,0" />
		  <Layer ID="9" Values="14,16,13,1,4,6,5,7,9,12,8,0" />
		  <Layer ID="59" Values="12,13,8,9,7,5,6,14,16,4,1,0" />
		  <Layer ID="60" Values="12,13,8,9,7,5,6,14,16,4,1,0" />
		  <Layer ID="61" Values="12,13,8,9,7,5,6,14,16,4,1,0" />
		  <Layer ID="62" Values="12,13,8,9,7,5,6,14,16,4,1,0" />
		</Layers>
		<Dirs>
		  <Dir ID="4" Values="12,13,8,6,5,14,16,4,1,0,9,7" />
		</Dirs>
	  </Action>
	  <Action Name="MeleeWMagic">
		<Layers>
		  <Layer ID="55" Values="8,6,12,13,9,5,14,16,4,1,0,7" />
		  <Layer ID="54" Values="8,6,12,13,5,9,14,16,4,1,0,7" />
		  <Layer ID="56" Values="8,6,12,13,5,9,14,16,4,1,0,7" />
		  <Layer ID="0" Values="14,16,13,9,1,7,4,5,6,8,0,12" />
		  <Layer ID="15" Values="14,16,13,7,4,9,1,5,12,6,8,0" />
		  <Layer ID="16" Values="14,16,13,7,9,4,1,5,12,6,8,0" />
		  <Layer ID="14" Values="14,16,13,7,9,4,1,5,12,6,8,0" />
		  <Layer ID="8" Values="14,16,13,1,4,6,5,7,8,0,12,9" />
		  <Layer ID="9" Values="14,16,13,1,4,7,5,6,8,0,12,9" />
		  <Layer ID="1" Values="14,16,13,1,4,7,5,6,8,0,12,9" />
		  <Layer ID="2" Values="14,16,13,1,4,7,5,6,8,0,12,9" />
		  <Layer ID="40" Values="12,13,8,6,9,5,7,14,16,4,1,0" />
		  <Layer ID="41" Values="12,13,8,6,9,5,7,14,16,4,1,0" />
		  <Layer ID="42" Values="12,13,8,6,9,5,7,14,16,4,1,0" />
		  <Layer ID="48" Values="12,13,8,6,9,5,14,16,7,4,1,0" />
		  <Layer ID="49" Values="12,13,8,6,9,5,7,14,16,4,1,0" />
		</Layers>
		<Dirs>
		  <Dir ID="4" Values="7,12,13,8,6,9,5,14,16,4,1,0" />
		  <Dir ID="0" Values="14,16,13,1,4,5,6,7,8,0,12,9" />
		</Dirs>
	  </Action>
	  <Action Name="FreeStand3">
		<Layers />
		<Dirs>
		  <Dir ID="0" Values="14,16,13,1,4,7,9,5,6,12,8,0" />
		  <Dir ID="4" Values="12,13,8,6,5,14,16,4,1,0,9,7" />
		  <Dir ID="7" Values="14,16,13,4,1,8,6,5,12,0,7,9" />
		</Dirs>
	  </Action>
	  <Action Name="FreeStand1">
		<Layers />
		<Dirs>
		  <Dir ID="4" Values="12,13,8,6,5,14,16,4,1,0,9,7" />
		  <Dir ID="0" Values="14,16,13,1,4,9,7,5,8,6,12,0" />
		  <Dir ID="1" Values="14,16,13,9,7,4,1,5,12,8,6,0" />
		  <Dir ID="2" Values="9,7,12,13,14,5,16,4,1,0,8,6" />
		</Dirs>
	  </Action>
	  <Action Name="FreeStand2">
		<Layers />
		<Dirs>
		  <Dir ID="4" Values="12,13,8,6,5,14,16,4,1,0,9,7" />
		  <Dir ID="0" Values="14,16,13,1,4,9,7,5,8,6,12,0" />
		  <Dir ID="1" Values="14,16,13,9,7,4,1,5,12,8,6,0" />
		  <Dir ID="2" Values="9,7,12,13,14,5,16,4,1,0,8,6" />
		</Dirs>
	  </Action>
	  <Action Name="FreeWound">
		<Layers />
		<Dirs>
		  <Dir ID="0" Values="14,16,13,1,4,7,9,5,6,12,8,0" />
		  <Dir ID="1" Values="14,16,13,7,9,4,1,5,12,6,8,0" />
		  <Dir ID="4" Values="12,13,8,6,5,14,16,4,1,0,9,7" />
		</Dirs>
	  </Action>
	  <Action Name="FreeDie">
		<Layers>
		  <Layer ID="101" Values="14,16,13,8,6,5,12,0,9,7,4,1" />
		  <Layer ID="102" Values="14,16,13,8,6,5,12,0,9,7,4,1" />
		  <Layer ID="103" Values="14,16,13,8,6,5,12,0,9,7,4,1" />
		  <Layer ID="23" Values="14,16,13,9,7,5,12,6,8,0,4,1" />
		  <Layer ID="24" Values="14,16,13,9,7,5,12,6,8,0,4,1" />
		  <Layer ID="25" Values="14,16,13,9,7,5,12,6,8,0,4,1" />
		  <Layer ID="9" Values="14,16,13,9,7,5,6,12,8,0,4,1" />
		  <Layer ID="10" Values="14,16,13,9,7,5,6,12,8,0,4,1" />
		  <Layer ID="11" Values="14,16,13,9,7,5,6,12,8,0,4,1" />
		  <Layer ID="12" Values="14,16,13,9,7,5,6,12,8,0,4,1" />
		</Layers>
		<Dirs />
	  </Action>
	  <Action Name="FreeAttack">
		<Layers>
		  <Layer ID="7" Values="14,16,13,1,4,6,8,5,12,0,7,9" />
		  <Layer ID="8" Values="14,16,13,1,4,6,8,5,7,9,12,0" />
		  <Layer ID="9" Values="14,16,13,1,4,6,5,7,9,12,8,0" />
		  <Layer ID="10" Values="14,16,13,1,4,6,5,7,9,12,8,0" />
		  <Layer ID="55" Values="12,13,9,7,5,6,8,14,16,4,1,0" />
		  <Layer ID="56" Values="12,13,7,9,5,6,8,14,16,4,1,0" />
		  <Layer ID="57" Values="12,13,9,7,5,8,6,14,16,4,1,0" />
		  <Layer ID="58" Values="12,13,9,7,5,8,6,14,16,4,1,0" />
		  <Layer ID="88" Values="14,16,13,4,1,8,7,5,6,12,0,9" />
		  <Layer ID="89" Values="14,16,13,4,1,8,7,5,6,12,0,9" />
		</Layers>
		<Dirs>
		  <Dir ID="0" Values="14,16,13,1,4,7,9,5,6,12,8,0" />
		  <Dir ID="1" Values="14,16,13,7,9,4,1,5,12,6,8,0" />
		  <Dir ID="4" Values="12,13,8,6,5,14,16,4,1,0,9,7" />
		  <Dir ID="7" Values="14,16,13,4,1,8,6,5,12,0,7,9" />
		</Dirs>
	  </Action>
	  <Action Name="FreeMagic">
		<Layers />
		<Dirs>
		  <Dir ID="0" Values="14,16,13,1,4,7,9,5,6,12,8,0" />
		  <Dir ID="4" Values="12,13,8,6,5,14,16,4,1,0,9,7" />
		</Dirs>
	  </Action>
	  <Action Name="SitDown">
		<Layers />
		<Dirs>
		  <Dir ID="0" Values="14,16,13,1,4,5,7,9,6,12,8,0" />
		  <Dir ID="1" Values="14,16,13,7,4,1,5,9,12,6,8,0" />
		  <Dir ID="4" Values="12,13,5,8,6,14,16,4,1,0,7,9" />
		  <Dir ID="6" Values="8,6,12,13,14,5,16,4,1,0,7,9" />
		  <Dir ID="7" Values="14,16,13,4,1,8,6,5,12,0,7,9" />
		</Dirs>
	  </Action>
	  <Action Name="DartThrow">
		<Layers>
		  <Layer ID="6" Values="14,16,13,1,4,6,8,5,7,9,12,0" />
		  <Layer ID="7" Values="14,16,13,1,4,6,5,7,9,12,8,0" />
		  <Layer ID="8" Values="14,16,13,1,4,6,5,7,9,12,8,0" />
		  <Layer ID="54" Values="12,13,8,9,7,5,6,14,16,4,1,0" />
		  <Layer ID="55" Values="12,13,8,9,7,5,6,14,16,4,1,0" />
		  <Layer ID="56" Values="12,13,8,9,7,5,6,14,16,4,1,0" />
		  <Layer ID="67" Values="8,6,12,13,7,5,14,16,4,1,0,9" />
		</Layers>
		<Dirs>
		  <Dir ID="0" Values="14,16,13,1,4,7,9,5,6,12,8,0" />
		  <Dir ID="4" Values="12,13,8,6,5,14,16,4,1,0,9,7" />
		</Dirs>
	  </Action>
	  <Action Name="MeleeWWound">
		<Layers />
		<Dirs>
		  <Dir ID="7" Values="14,16,13,4,1,8,6,5,12,0,7,9" />
		</Dirs>
	  </Action>
	  <Action Name="MeleeWDie">
		<Layers>
		  <Layer ID="10" Values="14,16,13,7,9,5,6,12,8,0,4,1" />
		  <Layer ID="11" Values="14,16,13,7,9,5,6,12,8,0,4,1" />
		  <Layer ID="12" Values="14,16,13,7,9,5,6,12,8,0,4,1" />
		  <Layer ID="13" Values="14,16,13,7,9,5,6,12,8,0,4,1" />
		  <Layer ID="14" Values="14,16,13,7,9,5,6,12,8,0,4,1" />
		  <Layer ID="114" Values="14,16,13,8,6,5,12,0,7,9,4,1" />
		  <Layer ID="115" Values="14,16,13,8,6,5,12,0,7,9,4,1" />
		  <Layer ID="116" Values="14,16,13,8,6,5,12,0,7,9,4,1" />
		  <Layer ID="117" Values="14,16,13,8,6,5,12,0,7,9,4,1" />
		  <Layer ID="118" Values="14,16,13,8,6,5,12,0,7,9,4,1" />
		  <Layer ID="119" Values="14,16,13,8,6,5,12,0,7,9,4,1" />
		</Layers>
		<Dirs>
		  <Dir ID="6" Values="8,6,12,13,14,5,16,4,1,0,7,9" />
		  <Dir ID="7" Values="14,16,13,4,1,8,6,5,12,0,7,9" />
		</Dirs>
	  </Action>
	  <Action Name="MeleeWWalk">
		<Layers />
		<Dirs>
		  <Dir ID="0" Values="14,16,13,1,4,5,9,7,6,12,8,0" />
		  <Dir ID="4" Values="12,13,8,6,5,14,16,4,1,0,9,7" />
		</Dirs>
	  </Action>
	  <Action Name="MeleeWRun">
		<Layers>
		  <Layer ID="3" Values="14,16,13,1,4,7,5,9,6,12,8,0" />
		  <Layer ID="4" Values="14,16,13,1,4,7,5,9,6,12,8,0" />
		  <Layer ID="5" Values="14,16,13,1,4,7,5,9,6,12,8,0" />
		  <Layer ID="6" Values="14,16,13,1,4,7,5,9,6,12,8,0" />
		  <Layer ID="7" Values="14,16,13,1,4,7,5,9,6,12,8,0" />
		  <Layer ID="8" Values="14,16,13,1,4,7,5,9,6,12,8,0" />
		  <Layer ID="2" Values="14,16,13,1,4,7,5,9,6,12,8,0" />
		  <Layer ID="0" Values="14,16,13,1,4,6,5,9,7,12,8,0" />
		  <Layer ID="1" Values="14,16,13,1,4,6,5,9,7,12,8,0" />
		  <Layer ID="10" Values="14,16,13,1,4,6,5,9,7,12,8,0" />
		  <Layer ID="11" Values="14,16,13,1,4,6,5,9,7,12,8,0" />
		  <Layer ID="52" Values="12,13,9,8,6,5,7,14,16,4,1,0" />
		  <Layer ID="50" Values="12,13,9,5,7,8,6,14,16,4,1,0" />
		  <Layer ID="51" Values="12,13,9,8,6,5,7,14,16,4,1,0" />
		  <Layer ID="53" Values="12,13,9,8,6,5,7,14,16,4,1,0" />
		  <Layer ID="54" Values="12,13,8,6,5,9,7,14,16,4,1,0" />
		  <Layer ID="55" Values="12,13,8,6,5,9,7,14,16,4,1,0" />
		  <Layer ID="56" Values="12,13,9,7,8,6,5,14,16,4,1,0" />
		</Layers>
		<Dirs>
		  <Dir ID="0" Values="14,16,13,1,4,5,9,7,6,12,8,0" />
		  <Dir ID="4" Values="12,13,9,7,5,8,6,14,16,4,1,0" />
		</Dirs>
	  </Action>
	  <Action Name="RangeWWalk">
		<Layers>
		  <Layer ID="31" Values="7,12,13,14,5,16,4,1,0,6,8,9" />
		  <Layer ID="32" Values="7,12,13,14,5,16,4,1,0,6,8,9" />
		  <Layer ID="33" Values="7,12,13,14,5,16,4,1,0,6,8,9" />
		  <Layer ID="34" Values="7,12,13,14,5,16,4,1,0,6,8,9" />
		</Layers>
		<Dirs>
		  <Dir ID="0" Values="14,16,13,1,4,7,5,6,12,8,0,9" />
		  <Dir ID="1" Values="14,16,13,7,4,1,5,12,6,8,0,9" />
		  <Dir ID="4" Values="12,13,9,8,6,5,14,16,4,1,0,7" />
		  <Dir ID="5" Values="8,6,12,13,9,5,14,16,4,1,0,7" />
		  <Dir ID="7" Values="14,16,13,4,1,8,6,5,12,0,7,9" />
		  <Dir ID="6" Values="8,6,12,13,14,5,16,4,1,0,7,9" />
		</Dirs>
	  </Action>
	  <Action Name="RangeWRun">
		<Layers>
		  <Layer ID="24" Values="7,12,13,14,5,16,4,1,0,6,8,9" />
		  <Layer ID="25" Values="7,12,13,14,5,16,4,1,0,6,8,9" />
		  <Layer ID="48" Values="12,13,9,8,5,6,14,16,4,1,0,7" />
		</Layers>
		<Dirs>
		  <Dir ID="0" Values="14,16,13,1,4,7,5,6,12,8,0,9" />
		  <Dir ID="1" Values="14,16,13,7,4,1,5,12,6,8,0,9" />
		  <Dir ID="4" Values="12,13,9,8,6,5,14,16,4,1,0,7" />
		  <Dir ID="5" Values="8,6,12,13,9,5,14,16,4,1,0,7" />
		  <Dir ID="6" Values="8,6,12,13,14,5,16,4,1,7,9,0" />
		  <Dir ID="7" Values="14,16,13,4,1,8,6,5,12,0,7,9" />
		</Dirs>
	  </Action>
	  <Action Name="DoubleWWalk">
		<Layers />
		<Dirs>
		  <Dir ID="0" Values="14,16,13,1,4,5,9,7,6,12,8,0" />
		  <Dir ID="4" Values="12,13,8,6,9,5,14,16,4,1,0,7" />
		</Dirs>
	  </Action>
	  <Action Name="DoubleWRun">
		<Layers />
		<Dirs>
		  <Dir ID="0" Values="14,16,13,1,4,7,5,6,12,0,9,8" />
		  <Dir ID="4" Values="12,13,8,6,9,5,14,16,7,4,0,1" />
		</Dirs>
	  </Action>
	</Female>
</CharacterActionSetLayerSort>